plascode/__init__.py
plascode/definitions.py
plascode/plascode.py
plascode/cli/__init__.py
plascode/cli/config.py
plascode/cli/inventory.py
plascode/cli/main.py
plascode/cli/publish.py
plascode/cli/script.py
plascode/cli/setup.py
plascode/cli/surreal.py
plascode/cli/sync.py
plascode/cli/task.py
plascode/cli/wingdbstub.py
plascode/cli/workspace.py
plascode/helpers/__init__.py
plascode/helpers/faker.py
plascode/helpers/general.py
plascode/helpers/loaders.py
plascode/helpers/models.py
plascode/helpers/surreal.py
plascode/logic/__init__.py
plascode/logic/crawler.py
plascode/logic/inventory.py
plascode/logic/plascode.py
plascode/mappers/__init__.py
plascode/mappers/inventory.py
plascode/models/__init__.py
plascode/models/base.py
plascode/models/config.py
plascode/models/enums.py
plascode/models/inventory.py
plascode/models/plascode.py
plascode/models/script.py
plascode/models/task.py
plascode/ports/__init__.py
plascode/ports/preferences.py
plascode/storage/__init__.py
plascode/storage/surreal.py
plascode-0.1.0.dist-info/AUTHORS.rst
plascode-0.1.0.dist-info/LICENSE
plascode-0.1.0.dist-info/METADATA
plascode-0.1.0.dist-info/WHEEL
plascode-0.1.0.dist-info/entry_points.txt
plascode-0.1.0.dist-info/top_level.txt
plascode-0.1.0.dist-info/RECORD
